mobypy/__init__.py
mobypy/thesaurus.py
mobypy/words.txt
mobypy-1.0.2.dist-info/LICENSE
mobypy-1.0.2.dist-info/METADATA
mobypy-1.0.2.dist-info/WHEEL
mobypy-1.0.2.dist-info/top_level.txt
mobypy-1.0.2.dist-info/RECORD
