Metadata-Version: 2.1
Name: mobypy
Version: 1.0.2
Summary: Python module for searching the Moby thesaurus
Home-page: https://github.com/blainemccarthy/mobypy
Author: Blaine McCarthy
Author-email: 42183028+blainemccarthy@users.noreply.github.com
License: MIT
Keywords: moby,thesaurus,synonyms,language,python
Platform: UNKNOWN
Classifier: Development Status :: 5 - Production/Stable
Classifier: Intended Audience :: Developers
Classifier: License :: OSI Approved :: Python Software Foundation License
Classifier: Operating System :: MacOS :: MacOS X
Classifier: Operating System :: Microsoft :: Windows
Classifier: Operating System :: POSIX
Classifier: Programming Language :: Python
Classifier: Topic :: Text Processing :: Linguistic
